LICENSE.md
MANIFEST.in
README.rst
setup.py
contourviz/__init__.py
contourviz/contourviz.py
contourviz.egg-info/PKG-INFO
contourviz.egg-info/SOURCES.txt
contourviz.egg-info/dependency_links.txt
contourviz.egg-info/entry_points.txt
contourviz.egg-info/not-zip-safe
contourviz.egg-info/requires.txt
contourviz.egg-info/top_level.txt
contourviz/results/collection_data.json
contourviz/results/index.html
contourviz/results/src/bootstrap.min.css
contourviz/results/src/bootstrap.min.js
contourviz/results/src/d3.min.js
contourviz/results/src/jquery-1.12.4.min.js
contourviz/results/src/script.js
contourviz/results/src/styles.css