Metadata-Version: 1.0
Name: contourviz
Version: 0.2.4
Summary: A package that charts musical contours into a web-based interactive using music21 and D3.js.
Home-page: https://github.com/cjwit/contourviz
Author: Christopher Witulski
Author-email: chris.witulski@gmail.com
License: BSD
Keywords: music21 music analysis javascript data visualization
Platform: UNKNOWN
